my_risk_mgmt/VaR.py
my_risk_mgmt/__init__.py
my_risk_mgmt/cov_matrix.py
my_risk_mgmt/linear_regression.py
my_risk_mgmt/simulation.py
my_risk_mgmt-0.2.0.dist-info/METADATA
my_risk_mgmt-0.2.0.dist-info/WHEEL
my_risk_mgmt-0.2.0.dist-info/top_level.txt
my_risk_mgmt-0.2.0.dist-info/RECORD
